{"type": "software configuration model", "name": "toybox-2007-11-07_00-11-20", "meta": {"extracted_from": "toybox-case-study/010_models/2007/2007-11-07_00-11-20.tar.gz"}, "num_variables": 31, "num_concrete_features": 30, "labels": {"CONFIG_CD": 5, "CONFIG_CD_P": 6, "CONFIG_DF": 17, "CONFIG_DF_PEDANTIC": 21, "CONFIG_EXIT": 26, "CONFIG_HELP": 30, "CONFIG_HELP_LONG": 13, "CONFIG_MDEV": 7, "CONFIG_MDEV_CONF": 23, "CONFIG_MKE2FS": 20, "CONFIG_MKE2FS_EXTENDED": 14, "CONFIG_MKE2FS_GEN": 27, "CONFIG_MKE2FS_JOURNAL": 16, "CONFIG_MKE2FS_LABEL": 1, "CONFIG_READLINK": 4, "CONFIG_READLINK_F": 22, "CONFIG_TOYBOX": 18, "CONFIG_TOYSH": 2, "CONFIG_TOYSH_ARRAYS": 25, "CONFIG_TOYSH_BUILTINS": 10, "CONFIG_TOYSH_ENVVARS": 8, "CONFIG_TOYSH_FLOWCTL": 3, "CONFIG_TOYSH_JOBCTL": 28, "CONFIG_TOYSH_LOCALS": 12, "CONFIG_TOYSH_PIPES": 29, "CONFIG_TOYSH_PROCARGS": 19, "CONFIG_TOYSH_PROFILE": 11, "CONFIG_TOYSH_QUOTES": 9, "CONFIG_TOYSH_TTY": 24, "CONFIG_TOYSH_WILDCARDS": 15}, "cnf_clauses": [[31], [-5, 31], [-6, 31], [-17, 31], [-21, 31], [-26, 31], [-30, 31], [-13, 31], [-7, 31], [-23, 31], [-20, 31], [-14, 31], [-27, 31], [-16, 31], [-1, 31], [-4, 31], [-22, 31], [-18, 31], [-2, 31], [-25, 31], [-10, 31], [-8, 31], [-3, 31], [-28, 31], [-12, 31], [-29, 31], [-19, 31], [-11, 31], [-9, 31], [-24, 31], [-15, 31], [17, -21], [9, -8], [-12, 8], [20, -1], [-10, 2], [20, -16], [-13, 30], [-25, 12], [2, -3], [-5], [20, -27], [-23, 7], [-28, 24], [-29, 2], [-26], [-11, 24], [-6], [-18], [2, -24], [4, -22], [9, -19], [-14, 20], [-15, 9], [-9, 2]], "structure": {"tree": {"type": "AND", "feature_literal": {"name": "__Root__", "negated": false}, "mandatory": true, "elements": [{"type": "CONCRETE", "feature_literal": {"name": "CONFIG_CD", "negated": false}, "mandatory": false}, {"type": "CONCRETE", "feature_literal": {"name": "CONFIG_CD_P", "negated": false}, "mandatory": false}, {"type": "CONCRETE", "feature_literal": {"name": "CONFIG_DF", "negated": false}, "mandatory": false}, {"type": "CONCRETE", "feature_literal": {"name": "CONFIG_DF_PEDANTIC", "negated": false}, "mandatory": false}, {"type": "CONCRETE", "feature_literal": {"name": "CONFIG_EXIT", "negated": false}, "mandatory": false}, {"type": "CONCRETE", "feature_literal": {"name": "CONFIG_HELP", "negated": false}, "mandatory": false}, {"type": "CONCRETE", "feature_literal": {"name": "CONFIG_HELP_LONG", "negated": false}, "mandatory": false}, {"type": "CONCRETE", "feature_literal": {"name": "CONFIG_MDEV", "negated": false}, "mandatory": false}, {"type": "CONCRETE", "feature_literal": {"name": "CONFIG_MDEV_CONF", "negated": false}, "mandatory": false}, {"type": "CONCRETE", "feature_literal": {"name": "CONFIG_MKE2FS", "negated": false}, "mandatory": false}, {"type": "CONCRETE", "feature_literal": {"name": "CONFIG_MKE2FS_EXTENDED", "negated": false}, "mandatory": false}, {"type": "CONCRETE", "feature_literal": {"name": "CONFIG_MKE2FS_GEN", "negated": false}, "mandatory": false}, {"type": "CONCRETE", "feature_literal": {"name": "CONFIG_MKE2FS_JOURNAL", "negated": false}, "mandatory": false}, {"type": "CONCRETE", "feature_literal": {"name": "CONFIG_MKE2FS_LABEL", "negated": false}, "mandatory": false}, {"type": "CONCRETE", "feature_literal": {"name": "CONFIG_READLINK", "negated": false}, "mandatory": false}, {"type": "CONCRETE", "feature_literal": {"name": "CONFIG_READLINK_F", "negated": false}, "mandatory": false}, {"type": "CONCRETE", "feature_literal": {"name": "CONFIG_TOYBOX", "negated": false}, "mandatory": false}, {"type": "CONCRETE", "feature_literal": {"name": "CONFIG_TOYSH", "negated": false}, "mandatory": false}, {"type": "CONCRETE", "feature_literal": {"name": "CONFIG_TOYSH_ARRAYS", "negated": false}, "mandatory": false}, {"type": "CONCRETE", "feature_literal": {"name": "CONFIG_TOYSH_BUILTINS", "negated": false}, "mandatory": false}, {"type": "CONCRETE", "feature_literal": {"name": "CONFIG_TOYSH_ENVVARS", "negated": false}, "mandatory": false}, {"type": "CONCRETE", "feature_literal": {"name": "CONFIG_TOYSH_FLOWCTL", "negated": false}, "mandatory": false}, {"type": "CONCRETE", "feature_literal": {"name": "CONFIG_TOYSH_JOBCTL", "negated": false}, "mandatory": false}, {"type": "CONCRETE", "feature_literal": {"name": "CONFIG_TOYSH_LOCALS", "negated": false}, "mandatory": false}, {"type": "CONCRETE", "feature_literal": {"name": "CONFIG_TOYSH_PIPES", "negated": false}, "mandatory": false}, {"type": "CONCRETE", "feature_literal": {"name": "CONFIG_TOYSH_PROCARGS", "negated": false}, "mandatory": false}, {"type": "CONCRETE", "feature_literal": {"name": "CONFIG_TOYSH_PROFILE", "negated": false}, "mandatory": false}, {"type": "CONCRETE", "feature_literal": {"name": "CONFIG_TOYSH_QUOTES", "negated": false}, "mandatory": false}, {"type": "CONCRETE", "feature_literal": {"name": "CONFIG_TOYSH_TTY", "negated": false}, "mandatory": false}, {"type": "CONCRETE", "feature_literal": {"name": "CONFIG_TOYSH_WILDCARDS", "negated": false}, "mandatory": false}]}, "rules": [{"type": "OR", "elements": [{"type": "VAR", "name": "CONFIG_DF", "negated": false, "auxiliary": false}, {"type": "VAR", "name": "CONFIG_DF_PEDANTIC", "negated": true, "auxiliary": false}]}, {"type": "OR", "elements": [{"type": "VAR", "name": "CONFIG_TOYSH_QUOTES", "negated": false, "auxiliary": false}, {"type": "VAR", "name": "CONFIG_TOYSH_ENVVARS", "negated": true, "auxiliary": false}]}, {"type": "OR", "elements": [{"type": "VAR", "name": "CONFIG_TOYSH_LOCALS", "negated": true, "auxiliary": false}, {"type": "VAR", "name": "CONFIG_TOYSH_ENVVARS", "negated": false, "auxiliary": false}]}, {"type": "OR", "elements": [{"type": "VAR", "name": "CONFIG_MKE2FS", "negated": false, "auxiliary": false}, {"type": "VAR", "name": "CONFIG_MKE2FS_LABEL", "negated": true, "auxiliary": false}]}, {"type": "OR", "elements": [{"type": "VAR", "name": "CONFIG_TOYSH_BUILTINS", "negated": true, "auxiliary": false}, {"type": "VAR", "name": "CONFIG_TOYSH", "negated": false, "auxiliary": false}]}, {"type": "OR", "elements": [{"type": "VAR", "name": "CONFIG_MKE2FS", "negated": false, "auxiliary": false}, {"type": "VAR", "name": "CONFIG_MKE2FS_JOURNAL", "negated": true, "auxiliary": false}]}, {"type": "OR", "elements": [{"type": "VAR", "name": "CONFIG_HELP_LONG", "negated": true, "auxiliary": false}, {"type": "VAR", "name": "CONFIG_HELP", "negated": false, "auxiliary": false}]}, {"type": "OR", "elements": [{"type": "VAR", "name": "CONFIG_TOYSH_ARRAYS", "negated": true, "auxiliary": false}, {"type": "VAR", "name": "CONFIG_TOYSH_LOCALS", "negated": false, "auxiliary": false}]}, {"type": "OR", "elements": [{"type": "VAR", "name": "CONFIG_TOYSH", "negated": false, "auxiliary": false}, {"type": "VAR", "name": "CONFIG_TOYSH_FLOWCTL", "negated": true, "auxiliary": false}]}, {"type": "VAR", "name": "CONFIG_CD", "negated": true, "auxiliary": false}, {"type": "OR", "elements": [{"type": "VAR", "name": "CONFIG_MKE2FS", "negated": false, "auxiliary": false}, {"type": "VAR", "name": "CONFIG_MKE2FS_GEN", "negated": true, "auxiliary": false}]}, {"type": "OR", "elements": [{"type": "VAR", "name": "CONFIG_MDEV_CONF", "negated": true, "auxiliary": false}, {"type": "VAR", "name": "CONFIG_MDEV", "negated": false, "auxiliary": false}]}, {"type": "OR", "elements": [{"type": "VAR", "name": "CONFIG_TOYSH_JOBCTL", "negated": true, "auxiliary": false}, {"type": "VAR", "name": "CONFIG_TOYSH_TTY", "negated": false, "auxiliary": false}]}, {"type": "OR", "elements": [{"type": "VAR", "name": "CONFIG_TOYSH_PIPES", "negated": true, "auxiliary": false}, {"type": "VAR", "name": "CONFIG_TOYSH", "negated": false, "auxiliary": false}]}, {"type": "VAR", "name": "CONFIG_EXIT", "negated": true, "auxiliary": false}, {"type": "OR", "elements": [{"type": "VAR", "name": "CONFIG_TOYSH_PROFILE", "negated": true, "auxiliary": false}, {"type": "VAR", "name": "CONFIG_TOYSH_TTY", "negated": false, "auxiliary": false}]}, {"type": "VAR", "name": "CONFIG_CD_P", "negated": true, "auxiliary": false}, {"type": "VAR", "name": "CONFIG_TOYBOX", "negated": true, "auxiliary": false}, {"type": "OR", "elements": [{"type": "VAR", "name": "CONFIG_TOYSH", "negated": false, "auxiliary": false}, {"type": "VAR", "name": "CONFIG_TOYSH_TTY", "negated": true, "auxiliary": false}]}, {"type": "OR", "elements": [{"type": "VAR", "name": "CONFIG_READLINK", "negated": false, "auxiliary": false}, {"type": "VAR", "name": "CONFIG_READLINK_F", "negated": true, "auxiliary": false}]}, {"type": "OR", "elements": [{"type": "VAR", "name": "CONFIG_TOYSH_QUOTES", "negated": false, "auxiliary": false}, {"type": "VAR", "name": "CONFIG_TOYSH_PROCARGS", "negated": true, "auxiliary": false}]}, {"type": "OR", "elements": [{"type": "VAR", "name": "CONFIG_MKE2FS_EXTENDED", "negated": true, "auxiliary": false}, {"type": "VAR", "name": "CONFIG_MKE2FS", "negated": false, "auxiliary": false}]}, {"type": "OR", "elements": [{"type": "VAR", "name": "CONFIG_TOYSH_WILDCARDS", "negated": true, "auxiliary": false}, {"type": "VAR", "name": "CONFIG_TOYSH_QUOTES", "negated": false, "auxiliary": false}]}, {"type": "OR", "elements": [{"type": "VAR", "name": "CONFIG_TOYSH_QUOTES", "negated": true, "auxiliary": false}, {"type": "VAR", "name": "CONFIG_TOYSH", "negated": false, "auxiliary": false}]}]}}